chemelem.py
chemelem-0.1.data/data/share/doc/chemelem/README.md
chemelem-0.1.dist-info/LICENSE
chemelem-0.1.dist-info/METADATA
chemelem-0.1.dist-info/WHEEL
chemelem-0.1.dist-info/entry_points.txt
chemelem-0.1.dist-info/top_level.txt
chemelem-0.1.dist-info/RECORD
