Metadata-Version: 2.1
Name: chemelem
Version: 0.1
Summary: Chemical elements with masses and radii
Author: Mariusz Radon
Author-email: mariusz.radon@uj.edu.pl
Classifier: Environment :: Console
Classifier: Intended Audience :: Science/Research
Classifier: License :: OSI Approved :: MIT License
Classifier: Natural Language :: English
Classifier: Programming Language :: Python
Classifier: Programming Language :: Python :: 3
License-File: LICENSE
